gempaterkini/__init__.py
earthquake_in_indonesia-0.0.4.dist-info/LICENSE
earthquake_in_indonesia-0.0.4.dist-info/METADATA
earthquake_in_indonesia-0.0.4.dist-info/WHEEL
earthquake_in_indonesia-0.0.4.dist-info/top_level.txt
earthquake_in_indonesia-0.0.4.dist-info/RECORD
