Metadata-Version: 2.1
Name: earthquake-in-indonesia
Version: 0.0.4
Summary: This package will help you to retrieve data from the [BMKG]
Home-page: https://github.com/Henzo-Kawaii/latest-information-earthquake-update--indonesia
Author: Hendra Kusuma
Author-email: hendrakusuma.vegas@gmail.com
Project-URL: Website, https://henzogagerz.blogspot.com/
Classifier: Programming Language :: Python :: 3
Classifier: License :: OSI Approved :: GNU General Public License v3 (GPLv3)
Classifier: Operating System :: OS Independent
Classifier: Development Status :: 4 - Beta
Requires-Python: >=3.6
License-File: LICENSE
